README.rst
setup.py
src/geoserver/__init__.py
src/geoserver/catalog.py
src/geoserver/layer.py
src/geoserver/layergroup.py
src/geoserver/namespace.py
src/geoserver/resource.py
src/geoserver/store.py
src/geoserver/style.py
src/geoserver/support.py
src/geoserver/util.py
src/geoserver/workspace.py
src/gsconfig.egg-info/PKG-INFO
src/gsconfig.egg-info/SOURCES.txt
src/gsconfig.egg-info/dependency_links.txt
src/gsconfig.egg-info/requires.txt
src/gsconfig.egg-info/top_level.txt