Metadata-Version: 1.0
Name: gsconfig
Version: 0.6.7
Summary: GeoServer REST Configuration
Home-page: http://github.com/opengeo/gsconfig.py
Author: David Winslow, Sebastian Benthall
Author-email: dwinslow@opengeo.org
License: MIT
Keywords: GeoServer REST Configuration
Platform: UNKNOWN
Classifier: Development Status :: 4 - Beta
Classifier: Intended Audience :: Developers
Classifier: Intended Audience :: Science/Research
Classifier: License :: OSI Approved :: MIT License
Classifier: Operating System :: OS Independent
Classifier: Programming Language :: Python
Classifier: Topic :: Scientific/Engineering :: GIS
